{
  "closed": 1,
  "data": [
    {
      "id": "PR_kwDONnH3xc6Hqrhc",
      "title": "update webpage tab to show my github projects and more",
      "url": "https://github.com/bophelo99/masterPortfolio/pull/9",
      "state": "MERGED",
      "mergedBy": {
        "avatarUrl": "https://avatars.githubusercontent.com/u/68306386?u=cb4c9c4465193fd2579a76799101ec0c73c632d6&v=4",
        "url": "https://github.com/bophelo99",
        "login": "bophelo99"
      },
      "createdAt": "2025-01-14T07:13:05Z",
      "number": 9,
      "changedFiles": 10,
      "additions": 1230,
      "deletions": 3,
      "baseRepository": {
        "name": "masterPortfolio",
        "url": "https://github.com/bophelo99/masterPortfolio",
        "owner": {
          "avatarUrl": "https://avatars.githubusercontent.com/u/68306386?u=cb4c9c4465193fd2579a76799101ec0c73c632d6&v=4",
          "login": "bophelo99",
          "url": "https://github.com/bophelo99"
        }
      }
    },
    {
      "id": "PR_kwDONnH3xc6HqkH5",
      "title": "Add tab to share my cv, contacts, and address and socials",
      "url": "https://github.com/bophelo99/masterPortfolio/pull/8",
      "state": "MERGED",
      "mergedBy": {
        "avatarUrl": "https://avatars.githubusercontent.com/u/68306386?u=cb4c9c4465193fd2579a76799101ec0c73c632d6&v=4",
        "url": "https://github.com/bophelo99",
        "login": "bophelo99"
      },
      "createdAt": "2025-01-14T06:46:44Z",
      "number": 8,
      "changedFiles": 5,
      "additions": 831,
      "deletions": 4,
      "baseRepository": {
        "name": "masterPortfolio",
        "url": "https://github.com/bophelo99/masterPortfolio",
        "owner": {
          "avatarUrl": "https://avatars.githubusercontent.com/u/68306386?u=cb4c9c4465193fd2579a76799101ec0c73c632d6&v=4",
          "login": "bophelo99",
          "url": "https://github.com/bophelo99"
        }
      }
    },
    {
      "id": "PR_kwDONnH3xc6HqemV",
      "title": "Add tab to show opensource contributions",
      "url": "https://github.com/bophelo99/masterPortfolio/pull/7",
      "state": "MERGED",
      "mergedBy": {
        "avatarUrl": "https://avatars.githubusercontent.com/u/68306386?u=cb4c9c4465193fd2579a76799101ec0c73c632d6&v=4",
        "url": "https://github.com/bophelo99",
        "login": "bophelo99"
      },
      "createdAt": "2025-01-14T06:26:05Z",
      "number": 7,
      "changedFiles": 27,
      "additions": 1536,
      "deletions": 4,
      "baseRepository": {
        "name": "masterPortfolio",
        "url": "https://github.com/bophelo99/masterPortfolio",
        "owner": {
          "avatarUrl": "https://avatars.githubusercontent.com/u/68306386?u=cb4c9c4465193fd2579a76799101ec0c73c632d6&v=4",
          "login": "bophelo99",
          "url": "https://github.com/bophelo99"
        }
      }
    },
    {
      "id": "PR_kwDONnH3xc6HqMIy",
      "title": "Add education webpage tab",
      "url": "https://github.com/bophelo99/masterPortfolio/pull/6",
      "state": "MERGED",
      "mergedBy": {
        "avatarUrl": "https://avatars.githubusercontent.com/u/68306386?u=cb4c9c4465193fd2579a76799101ec0c73c632d6&v=4",
        "url": "https://github.com/bophelo99",
        "login": "bophelo99"
      },
      "createdAt": "2025-01-14T05:10:14Z",
      "number": 6,
      "changedFiles": 15,
      "additions": 941,
      "deletions": 5,
      "baseRepository": {
        "name": "masterPortfolio",
        "url": "https://github.com/bophelo99/masterPortfolio",
        "owner": {
          "avatarUrl": "https://avatars.githubusercontent.com/u/68306386?u=cb4c9c4465193fd2579a76799101ec0c73c632d6&v=4",
          "login": "bophelo99",
          "url": "https://github.com/bophelo99"
        }
      }
    },
    {
      "id": "PR_kwDONnH3xc6HjLFt",
      "title": "Adding experience webpage tab",
      "url": "https://github.com/bophelo99/masterPortfolio/pull/5",
      "state": "MERGED",
      "mergedBy": {
        "avatarUrl": "https://avatars.githubusercontent.com/u/68306386?u=cb4c9c4465193fd2579a76799101ec0c73c632d6&v=4",
        "url": "https://github.com/bophelo99",
        "login": "bophelo99"
      },
      "createdAt": "2025-01-13T15:17:48Z",
      "number": 5,
      "changedFiles": 8,
      "additions": 1079,
      "deletions": 4,
      "baseRepository": {
        "name": "masterPortfolio",
        "url": "https://github.com/bophelo99/masterPortfolio",
        "owner": {
          "avatarUrl": "https://avatars.githubusercontent.com/u/68306386?u=cb4c9c4465193fd2579a76799101ec0c73c632d6&v=4",
          "login": "bophelo99",
          "url": "https://github.com/bophelo99"
        }
      }
    },
    {
      "id": "PR_kwDONnH3xc6HdMn6",
      "title": "Masterpotfolio mVP",
      "url": "https://github.com/bophelo99/masterPortfolio/pull/4",
      "state": "MERGED",
      "mergedBy": {
        "avatarUrl": "https://avatars.githubusercontent.com/u/68306386?u=cb4c9c4465193fd2579a76799101ec0c73c632d6&v=4",
        "url": "https://github.com/bophelo99",
        "login": "bophelo99"
      },
      "createdAt": "2025-01-12T15:42:46Z",
      "number": 4,
      "changedFiles": 1784,
      "additions": 209000,
      "deletions": 1,
      "baseRepository": {
        "name": "masterPortfolio",
        "url": "https://github.com/bophelo99/masterPortfolio",
        "owner": {
          "avatarUrl": "https://avatars.githubusercontent.com/u/68306386?u=cb4c9c4465193fd2579a76799101ec0c73c632d6&v=4",
          "login": "bophelo99",
          "url": "https://github.com/bophelo99"
        }
      }
    },
    {
      "id": "PR_kwDONnH3xc6Hcz1S",
      "title": "Masterpotfolio Readme File check",
      "url": "https://github.com/bophelo99/masterPortfolio/pull/2",
      "state": "MERGED",
      "mergedBy": {
        "avatarUrl": "https://avatars.githubusercontent.com/u/68306386?u=cb4c9c4465193fd2579a76799101ec0c73c632d6&v=4",
        "url": "https://github.com/bophelo99",
        "login": "bophelo99"
      },
      "createdAt": "2025-01-12T11:06:24Z",
      "number": 2,
      "changedFiles": 5,
      "additions": 24,
      "deletions": 1,
      "baseRepository": {
        "name": "masterPortfolio",
        "url": "https://github.com/bophelo99/masterPortfolio",
        "owner": {
          "avatarUrl": "https://avatars.githubusercontent.com/u/68306386?u=cb4c9c4465193fd2579a76799101ec0c73c632d6&v=4",
          "login": "bophelo99",
          "url": "https://github.com/bophelo99"
        }
      }
    },
    {
      "id": "PR_kwDONnH3xc6HcxsQ",
      "title": "Masterpotfolio WORKFLOW init",
      "url": "https://github.com/bophelo99/masterPortfolio/pull/1",
      "state": "MERGED",
      "mergedBy": {
        "avatarUrl": "https://avatars.githubusercontent.com/u/68306386?u=cb4c9c4465193fd2579a76799101ec0c73c632d6&v=4",
        "url": "https://github.com/bophelo99",
        "login": "bophelo99"
      },
      "createdAt": "2025-01-12T10:39:41Z",
      "number": 1,
      "changedFiles": 3,
      "additions": 86,
      "deletions": 0,
      "baseRepository": {
        "name": "masterPortfolio",
        "url": "https://github.com/bophelo99/masterPortfolio",
        "owner": {
          "avatarUrl": "https://avatars.githubusercontent.com/u/68306386?u=cb4c9c4465193fd2579a76799101ec0c73c632d6&v=4",
          "login": "bophelo99",
          "url": "https://github.com/bophelo99"
        }
      }
    },
    {
      "id": "PR_kwDOMIyk3c5yUxBQ",
      "title": "Bug fix revert",
      "url": "https://github.com/bophelo99/jbbmo-Introduction-to-Git-and-GitHub/pull/2",
      "state": "MERGED",
      "mergedBy": {
        "avatarUrl": "https://avatars.githubusercontent.com/u/68306386?u=cb4c9c4465193fd2579a76799101ec0c73c632d6&v=4",
        "url": "https://github.com/bophelo99",
        "login": "bophelo99"
      },
      "createdAt": "2024-06-13T07:44:02Z",
      "number": 2,
      "changedFiles": 0,
      "additions": 0,
      "deletions": 0,
      "baseRepository": {
        "name": "jbbmo-Introduction-to-Git-and-GitHub",
        "url": "https://github.com/bophelo99/jbbmo-Introduction-to-Git-and-GitHub",
        "owner": {
          "avatarUrl": "https://avatars.githubusercontent.com/u/68306386?u=cb4c9c4465193fd2579a76799101ec0c73c632d6&v=4",
          "login": "bophelo99",
          "url": "https://github.com/bophelo99"
        }
      }
    },
    {
      "id": "PR_kwDOMIyk3c5yUp3K",
      "title": "fix footer",
      "url": "https://github.com/bophelo99/jbbmo-Introduction-to-Git-and-GitHub/pull/1",
      "state": "MERGED",
      "mergedBy": {
        "avatarUrl": "https://avatars.githubusercontent.com/u/68306386?u=cb4c9c4465193fd2579a76799101ec0c73c632d6&v=4",
        "url": "https://github.com/bophelo99",
        "login": "bophelo99"
      },
      "createdAt": "2024-06-13T07:27:47Z",
      "number": 1,
      "changedFiles": 1,
      "additions": 1,
      "deletions": 1,
      "baseRepository": {
        "name": "jbbmo-Introduction-to-Git-and-GitHub",
        "url": "https://github.com/bophelo99/jbbmo-Introduction-to-Git-and-GitHub",
        "owner": {
          "avatarUrl": "https://avatars.githubusercontent.com/u/68306386?u=cb4c9c4465193fd2579a76799101ec0c73c632d6&v=4",
          "login": "bophelo99",
          "url": "https://github.com/bophelo99"
        }
      }
    },
    {
      "id": "PR_kwDOGqp3Ec5xJzEx",
      "title": " merge operation",
      "url": "https://github.com/ibm-developer-skills-network/jbbmo-Introduction-to-Git-and-GitHub/pull/30491",
      "state": "CLOSED",
      "mergedBy": null,
      "createdAt": "2024-05-31T17:53:27Z",
      "number": 30491,
      "changedFiles": 1,
      "additions": 1,
      "deletions": 1,
      "baseRepository": {
        "name": "jbbmo-Introduction-to-Git-and-GitHub",
        "url": "https://github.com/ibm-developer-skills-network/jbbmo-Introduction-to-Git-and-GitHub",
        "owner": {
          "avatarUrl": "https://avatars.githubusercontent.com/u/70551872?v=4",
          "login": "ibm-developer-skills-network",
          "url": "https://github.com/ibm-developer-skills-network"
        }
      }
    }
  ],
  "merged": 10,
  "open": 0,
  "totalCount": 11
}
